torchstudio/__init__.py
torchstudio/version.py
torchstudio/image_processing/__init__.py
torchstudio/image_processing/blur.py
torchstudio/image_processing/layout.py
torchstudio/plot/__init__.py
torchstudio/plot/attention.py
torchstudio/plot/bbox.py
torchstudio/rl/bandit_problem.py
torchstudio/rl/tic_tac_toe.py
torchstudio/rl/grpo/make_llm_dataset.py
torchstudio/rl/grpo/make_vlm_dataset.py
torchstudio/rl/grpo/train_llm.py
torchstudio/rl/grpo/train_vlm.py
torchstudio/utils/__init__.py
torchstudio/utils/iou.py
torchstudio-0.0.2.dist-info/METADATA
torchstudio-0.0.2.dist-info/WHEEL
torchstudio-0.0.2.dist-info/licenses/LICENSE
torchstudio-0.0.2.dist-info/RECORD
