Metadata-Version: 2.4
Name: torchstudio
Version: 0.0.2
Summary: Deep Learning Experiment
Project-URL: Homepage, https://github.com/jiauzhang/torchstudio
Author-email: Jiau Zhang <jiauzhang@163.com>
License:                     GNU GENERAL PUBLIC LICENSE
License-File: LICENSE
Keywords: Artificial Intelligence,Deep Learning,PyTorch
Classifier: Topic :: Scientific/Engineering :: Artificial Intelligence
Requires-Python: >=3.10
Requires-Dist: conippets>=0.1.8
Requires-Dist: matplotlib
Requires-Dist: nnm
Requires-Dist: pillow
Requires-Dist: trl>=0.23.0
Provides-Extra: dev
Requires-Dist: pytest>=8.3.4; extra == 'dev'
